README.txt
setup.py
collective/__init__.py
collective.groupdashboard.egg-info/PKG-INFO
collective.groupdashboard.egg-info/SOURCES.txt
collective.groupdashboard.egg-info/dependency_links.txt
collective.groupdashboard.egg-info/entry_points.txt
collective.groupdashboard.egg-info/namespace_packages.txt
collective.groupdashboard.egg-info/not-zip-safe
collective.groupdashboard.egg-info/requires.txt
collective.groupdashboard.egg-info/top_level.txt
collective/groupdashboard/__init__.py
collective/groupdashboard/browser.py
collective/groupdashboard/configure.zcml
collective/groupdashboard/interfaces.py
collective/groupdashboard/storage.py
collective/groupdashboard/tests.py
collective/groupdashboard/browser_templates/dashboard.pt
collective/groupdashboard/browser_templates/manage-group.pt
collective/groupdashboard/browser_templates/manage.pt
collective/groupdashboard/profiles/default/browserlayer.xml
collective/groupdashboard/profiles/default/metadata.xml
collective/groupdashboard/profiles/default/rolemap.xml
docs/HISTORY.txt
docs/INSTALL.txt
docs/LICENSE.GPL
docs/LICENSE.txt