Metadata-Version: 1.0
Name: collective.groupdashboard
Version: 1.0b2
Summary: Assign portlets to users' dashboards on a per-group basis
Home-page: http://pypi.python.org/pypi/collective.groupdashboard
Author: Martin Aspeli
Author-email: optilude@gmail.com
License: GPL
Keywords: plone group portlet dashboard
Platform: UNKNOWN
Classifier: Framework :: Plone
Classifier: Programming Language :: Python
Classifier: Topic :: Software Development :: Libraries :: Python Modules
